{
  "bg": 109, 
  "temp": "absolute", 
  "snoozeBG": 65, 
  "predBGs": {
    "IOB": [
      109, 
      104, 
      100, 
      96, 
      92, 
      88, 
      85, 
      82, 
      80, 
      78, 
      76, 
      75, 
      75, 
      75, 
      74, 
      74, 
      74, 
      74, 
      75, 
      75, 
      75, 
      76, 
      76, 
      77, 
      78, 
      78, 
      79, 
      79, 
      80, 
      81, 
      81, 
      82, 
      82, 
      82, 
      83
    ]
  }, 
  "reason": "COB: 0, Dev: -23, BGI: -1.12, ISF: 70, Target: 95; Eventual BG 65 < 95, setting -1.125U/hr, but 30m left and 0 ~ req 0U/hr: no action required", 
  "COB": 0, 
  "eventualBG": 65, 
  "tick": -5, 
  "IOB": 0.297
}