{
  "bg": 104, 
  "temp": "absolute", 
  "snoozeBG": 176, 
  "predBGs": {
    "COB": [
      104, 
      102, 
      100, 
      97, 
      94, 
      90, 
      86, 
      81, 
      76, 
      71, 
      65, 
      59, 
      52, 
      44, 
      39
    ], 
    "aCOB": [
      104, 
      108, 
      112, 
      115, 
      117, 
      119, 
      120, 
      121, 
      121, 
      121, 
      120, 
      119, 
      117, 
      114, 
      111, 
      107, 
      104, 
      101, 
      99, 
      97, 
      97, 
      96, 
      96, 
      97, 
      98, 
      99, 
      101, 
      103, 
      106, 
      109, 
      113, 
      117, 
      121, 
      126, 
      131, 
      137, 
      143, 
      150, 
      156, 
      162, 
      167, 
      173, 
      179
    ], 
    "IOB": [
      104, 
      102, 
      99, 
      95, 
      91, 
      85, 
      79, 
      72, 
      65, 
      57, 
      48, 
      39, 
      39
    ]
  }, 
  "reason": "COB: 60, Dev: -15, BGI: -5.67, ISF: 90, Target: 100; Eventual BG 39 < 100, bolus snooze: eventual BG range 39-176, temp 0.9 ~ req 0.9U/hr", 
  "COB": 60, 
  "eventualBG": 39, 
  "tick": -9, 
  "IOB": 2.732
}