{
  "bg": 145, 
  "temp": "absolute", 
  "snoozeBG": 157, 
  "predBGs": {
    "COB": [
      145, 
      153, 
      159, 
      164, 
      169, 
      172, 
      174, 
      176, 
      177, 
      177, 
      177, 
      177, 
      177, 
      176, 
      175, 
      173, 
      172, 
      170, 
      167, 
      165, 
      163, 
      160, 
      158, 
      155, 
      153, 
      151, 
      150, 
      148, 
      147, 
      147, 
      146, 
      145, 
      145, 
      144
    ], 
    "aCOB": [
      145, 
      148, 
      150, 
      151, 
      151, 
      151, 
      150, 
      148, 
      147, 
      146, 
      144, 
      143, 
      142, 
      140, 
      139, 
      138, 
      137, 
      136, 
      135, 
      135, 
      135, 
      135, 
      135, 
      136, 
      137, 
      138, 
      139, 
      141, 
      142, 
      143, 
      144, 
      145, 
      146, 
      146, 
      146, 
      147, 
      146
    ], 
    "IOB": [
      145, 
      152, 
      158, 
      161, 
      162, 
      162, 
      161, 
      158, 
      154, 
      149, 
      143, 
      136, 
      128, 
      120, 
      113, 
      106, 
      99, 
      93, 
      87, 
      82, 
      78, 
      74, 
      70, 
      67, 
      65, 
      63, 
      62, 
      60, 
      59, 
      59, 
      58, 
      57, 
      57, 
      56
    ]
  }, 
  "rate": 2.05, 
  "reason": "COB: 17, Dev: 92, BGI: -6.82, ISF: 89, Target: 80; Eventual BG 144 >= 80, temp 1.125<2.05U/hr", 
  "COB": 17, 
  "eventualBG": 144, 
  "duration": 30, 
  "tick": "+12", 
  "IOB": 1.678
}