[
  {
    "created_at": "2016-12-04T21:42:03.882Z", 
    "mmtune": {
      "scanDetails": [
        [
          "916.540", 
          5, 
          -90
        ], 
        [
          "916.564", 
          5, 
          -85
        ], 
        [
          "916.588", 
          5, 
          -84
        ], 
        [
          "916.612", 
          5, 
          -83
        ], 
        [
          "916.636", 
          5, 
          -83
        ], 
        [
          "916.660", 
          5, 
          -86
        ], 
        [
          "916.684", 
          5, 
          -90
        ]
      ], 
      "setFreq": 916.636, 
      "usedDefault": false, 
      "timestamp": "2016-12-04T21:39:15.000Z"
    }, 
    "pump": {
      "battery": {
        "status": "normal", 
        "voltage": 1.54
      }, 
      "status": {
        "status": "normal", 
        "timestamp": "2016-12-04T21:39:39.000Z", 
        "bolusing": false, 
        "suspended": false
      }, 
      "reservoir": 117.75, 
      "clock": "2016-12-04T13:39:37-08:00"
    }, 
    "openaps": {
      "suggested": {
        "bg": 112, 
        "temp": "absolute", 
        "snoozeBG": 140, 
        "timestamp": "2016-12-04T21:41:46.000Z", 
        "predBGs": {
          "COB": [
            112, 
            118, 
            123, 
            127, 
            131, 
            133, 
            135, 
            137, 
            139, 
            140, 
            142, 
            143, 
            143, 
            144, 
            145, 
            145, 
            146, 
            146, 
            147, 
            149, 
            150, 
            152, 
            154, 
            156, 
            159, 
            162, 
            165, 
            168, 
            171, 
            175, 
            178, 
            182, 
            185, 
            188, 
            192, 
            195, 
            199, 
            202, 
            205, 
            208, 
            211, 
            214, 
            216
          ], 
          "aCOB": [
            112, 
            119, 
            125, 
            130, 
            134, 
            138, 
            141, 
            143, 
            146, 
            148, 
            150, 
            151, 
            153, 
            154, 
            155, 
            156, 
            157, 
            158, 
            159, 
            161, 
            162, 
            164, 
            167, 
            169, 
            172, 
            175, 
            178, 
            182, 
            185, 
            188, 
            191, 
            195, 
            198, 
            201, 
            204, 
            208, 
            211, 
            214, 
            216, 
            219, 
            221, 
            224, 
            226
          ], 
          "IOB": [
            112, 
            117, 
            121, 
            124, 
            125, 
            124, 
            123, 
            121, 
            117, 
            114, 
            109, 
            103, 
            97, 
            91, 
            84, 
            78, 
            72, 
            66, 
            61, 
            56, 
            52, 
            48, 
            44, 
            41, 
            39
          ]
        }, 
        "reason": "COB: 32, Dev: 54, BGI: -2.84, ISF: 89, Target: 80; Eventual BG 216 >= 80, temp 2.2 >~ req 1.9U/hr", 
        "COB": 32, 
        "eventualBG": 216, 
        "tick": "+7", 
        "IOB": 1.286
      }, 
      "iob": {
        "netbasalinsulin": -0.25, 
        "timestamp": "2016-12-04T21:39:37.000Z", 
        "activity": 0.0064, 
        "basaliob": 0.237, 
        "hightempinsulin": 0.6, 
        "bolussnooze": 0.323, 
        "iob": 1.286
      }
    }, 
    "uploader": {
      "battery": 100, 
      "batteryVoltage": 4378
    }, 
    "device": "openaps://indy-e1", 
    "_id": "58448dab726928d7151b1bc8"
  }
]