{
  "bg": 114, 
  "temp": "absolute", 
  "snoozeBG": 80, 
  "recieved": true, 
  "predBGs": {
    "IOB": [
      114, 
      111, 
      109, 
      106, 
      104, 
      102, 
      100, 
      98, 
      96, 
      95, 
      93, 
      92, 
      92, 
      91, 
      91, 
      90, 
      89, 
      89, 
      88, 
      88, 
      87, 
      87, 
      87, 
      86
    ]
  }, 
  "reason": "COB: 0, Dev: -26, BGI: 1.68, ISF: 80, Target: 110; Eventual BG 80 < 110, setting -0.85U/hr", 
  "rate": 0.0, 
  "COB": 0, 
  "eventualBG": 80, 
  "timestamp": "2016-12-01T17:09:42.249088", 
  "duration": 30, 
  "tick": -3, 
  "IOB": 0.097
}