{
  "bg": 98, 
  "temp": "absolute", 
  "snoozeBG": 103, 
  "recieved": true, 
  "predBGs": {
    "IOB": [
      98, 
      99, 
      99, 
      100, 
      100, 
      101, 
      102, 
      102, 
      103, 
      103, 
      103, 
      103, 
      103, 
      103, 
      103, 
      103, 
      103, 
      103, 
      103, 
      103, 
      102, 
      102, 
      102, 
      101, 
      101, 
      101, 
      100, 
      100, 
      100, 
      100, 
      99
    ]
  }, 
  "reason": "COB: 0, Dev: -1, BGI: 0.77, ISF: 90, Target: 100; Eventual BG 103 > 100 but Min. Delta 0.58 < Exp. Delta 0.6; setting current basal of 0.525 as temp. Setting neutral temp basal of 0.525U/hr", 
  "rate": 0.8, 
  "COB": 0, 
  "eventualBG": 103, 
  "timestamp": "2016-12-18T03:36:29.236889", 
  "duration": 22, 
  "tick": "+1", 
  "IOB": -0.063
}