[
  {
    "trend_arrow": "45_UP", 
    "display_time": "2016-12-31T20:49:59-08:00", 
    "noise": 1, 
    "direction": "FortyFiveUp", 
    "system_time": "2017-01-01T04:49:19-08:00", 
    "sgv": 147, 
    "dateString": "2016-12-31T20:49:59-08:00", 
    "device": "openaps://indy-e1/cgm", 
    "unfiltered": 190112, 
    "rssi": 186, 
    "date": 1483246199000.0, 
    "filtered": 179744, 
    "type": "sgv", 
    "glucose": 147
  }, 
  {
    "trend_arrow": "FLAT", 
    "display_time": "2016-12-31T20:44:59-08:00", 
    "noise": 1, 
    "direction": "Flat", 
    "system_time": "2017-01-01T04:44:19-08:00", 
    "sgv": 138, 
    "dateString": "2016-12-31T20:44:59-08:00", 
    "device": "openaps://indy-e1/cgm", 
    "unfiltered": 181088, 
    "rssi": 180, 
    "date": 1483245899000.0, 
    "filtered": 175584, 
    "type": "sgv", 
    "glucose": 138
  }, 
  {
    "trend_arrow": "FLAT", 
    "display_time": "2016-12-31T20:39:59-08:00", 
    "noise": 1, 
    "direction": "Flat", 
    "system_time": "2017-01-01T04:39:19-08:00", 
    "sgv": 134, 
    "dateString": "2016-12-31T20:39:59-08:00", 
    "device": "openaps://indy-e1/cgm", 
    "unfiltered": 176576, 
    "rssi": 183, 
    "date": 1483245599000.0, 
    "filtered": 171936, 
    "type": "sgv", 
    "glucose": 134
  }, 
  {
    "trend_arrow": "FLAT", 
    "display_time": "2016-12-31T20:34:59-08:00", 
    "noise": 1, 
    "direction": "Flat", 
    "system_time": "2017-01-01T04:34:19-08:00", 
    "sgv": 132, 
    "dateString": "2016-12-31T20:34:59-08:00", 
    "device": "openaps://indy-e1/cgm", 
    "unfiltered": 174976, 
    "rssi": 173, 
    "date": 1483245299000.0, 
    "filtered": 168288, 
    "type": "sgv", 
    "glucose": 132
  }, 
  {
    "trend_arrow": "FLAT", 
    "display_time": "2016-12-31T20:29:59-08:00", 
    "noise": 1, 
    "direction": "Flat", 
    "system_time": "2017-01-01T04:29:20-08:00", 
    "sgv": 128, 
    "dateString": "2016-12-31T20:29:59-08:00", 
    "device": "openaps://indy-e1/cgm", 
    "unfiltered": 170496, 
    "rssi": 441, 
    "date": 1483244999000.0, 
    "filtered": 164544, 
    "type": "sgv", 
    "glucose": 128
  }, 
  {
    "trend_arrow": "45_UP", 
    "display_time": "2016-12-31T20:24:59-08:00", 
    "noise": 1, 
    "direction": "FortyFiveUp", 
    "system_time": "2017-01-01T04:24:19-08:00", 
    "sgv": 123, 
    "dateString": "2016-12-31T20:24:59-08:00", 
    "device": "openaps://indy-e1/cgm", 
    "unfiltered": 165792, 
    "rssi": 186, 
    "date": 1483244699000.0, 
    "filtered": 159840, 
    "type": "sgv", 
    "glucose": 123
  }
]