[
  {
    "trend_arrow": "FLAT", 
    "display_time": "2017-01-07T20:43:32-08:00", 
    "noise": 1, 
    "direction": "Flat", 
    "system_time": "2017-01-08T04:29:34-08:00", 
    "sgv": 85, 
    "dateString": "2017-01-07T20:43:32-08:00", 
    "device": "openaps://indy-e1/cgm", 
    "unfiltered": 92272, 
    "rssi": 179, 
    "date": 1483850612000.0, 
    "filtered": 96224, 
    "type": "sgv", 
    "glucose": 85
  }, 
  {
    "trend_arrow": "45_DOWN", 
    "display_time": "2017-01-07T20:38:32-08:00", 
    "noise": 1, 
    "direction": "FortyFiveDown", 
    "system_time": "2017-01-08T04:24:34-08:00", 
    "sgv": 90, 
    "dateString": "2017-01-07T20:38:32-08:00", 
    "device": "openaps://indy-e1/cgm", 
    "unfiltered": 96272, 
    "rssi": 187, 
    "date": 1483850312000.0, 
    "filtered": 100256, 
    "type": "sgv", 
    "glucose": 90
  }, 
  {
    "trend_arrow": "45_DOWN", 
    "display_time": "2017-01-07T20:33:32-08:00", 
    "noise": 1, 
    "direction": "FortyFiveDown", 
    "system_time": "2017-01-08T04:19:34-08:00", 
    "sgv": 92, 
    "dateString": "2017-01-07T20:33:32-08:00", 
    "device": "openaps://indy-e1/cgm", 
    "unfiltered": 98384, 
    "rssi": 187, 
    "date": 1483850012000.0, 
    "filtered": 105968, 
    "type": "sgv", 
    "glucose": 92
  }, 
  {
    "trend_arrow": "45_DOWN", 
    "display_time": "2017-01-07T20:28:32-08:00", 
    "noise": 1, 
    "direction": "FortyFiveDown", 
    "system_time": "2017-01-08T04:14:34-08:00", 
    "sgv": 95, 
    "dateString": "2017-01-07T20:28:32-08:00", 
    "device": "openaps://indy-e1/cgm", 
    "unfiltered": 101056, 
    "rssi": 185, 
    "date": 1483849712000.0, 
    "filtered": 112736, 
    "type": "sgv", 
    "glucose": 95
  }, 
  {
    "trend_arrow": "45_DOWN", 
    "display_time": "2017-01-07T20:23:33-08:00", 
    "noise": 1, 
    "direction": "FortyFiveDown", 
    "system_time": "2017-01-08T04:09:34-08:00", 
    "sgv": 104, 
    "dateString": "2017-01-07T20:23:33-08:00", 
    "device": "openaps://indy-e1/cgm", 
    "unfiltered": 108896, 
    "rssi": 432, 
    "date": 1483849413000.0, 
    "filtered": 119616, 
    "type": "sgv", 
    "glucose": 104
  }, 
  {
    "trend_arrow": "45_DOWN", 
    "display_time": "2017-01-07T20:18:32-08:00", 
    "noise": 1, 
    "direction": "FortyFiveDown", 
    "system_time": "2017-01-08T04:04:34-08:00", 
    "sgv": 113, 
    "dateString": "2017-01-07T20:18:32-08:00", 
    "device": "openaps://indy-e1/cgm", 
    "unfiltered": 116448, 
    "rssi": 186, 
    "date": 1483849112000.0, 
    "filtered": 126208, 
    "type": "sgv", 
    "glucose": 113
  }
]