{
  "device": "openaps://indy-e1", 
  "pump": {
    "battery": {
      "status": "normal", 
      "voltage": 1.45
    }, 
    "status": {
      "status": "normal", 
      "timestamp": "2016-12-01T14:10:49.000Z", 
      "bolusing": false, 
      "suspended": false
    }, 
    "reservoir": 90.175, 
    "clock": "2016-12-01T06:10:20-08:00"
  }, 
  "uploader": {
    "battery": 100, 
    "batteryVoltage": 4376
  }, 
  "openaps": {
    "suggested": {
      "bg": 83, 
      "temp": "absolute", 
      "snoozeBG": 103, 
      "timestamp": "2016-12-01T14:13:08.000Z", 
      "reason": "COB: 0, Dev: -13, BGI: 0.89, ISF: 71, Target: 104; Eventual BG 103 < 104, 21m@-0.575 = -0.201 < req -0.02824858757062147-0.1725", 
      "rate": 0.525, 
      "COB": 0, 
      "eventualBG": 103, 
      "duration": 30, 
      "tick": "+0", 
      "IOB": -0.462
    }, 
    "iob": {
      "netbasalinsulin": -0.35, 
      "timestamp": "2016-12-01T14:10:20.000Z", 
      "activity": -0.0025, 
      "basaliob": -0.462, 
      "hightempinsulin": 0.25, 
      "bolussnooze": 0, 
      "iob": -0.462
    }, 
    "enacted": {
      "bg": 83, 
      "temp": "absolute", 
      "snoozeBG": 103, 
      "recieved": true, 
      "predBGs": {
        "IOB": [
          83, 
          82, 
          81, 
          81, 
          81, 
          81, 
          81, 
          82, 
          83, 
          85, 
          86, 
          88, 
          90, 
          92, 
          94, 
          96, 
          98, 
          100, 
          101, 
          103, 
          105, 
          106, 
          107, 
          109, 
          110, 
          111, 
          111, 
          112, 
          113, 
          113, 
          114, 
          114, 
          114, 
          115
        ]
      }, 
      "rate": 0.525, 
      "reason": "COB: 0, Dev: -13, BGI: 0.89, ISF: 71, Target: 104; Eventual BG 103 < 104, 21m@-0.575 = -0.201 < req -0.02824858757062147-0.1725", 
      "COB": 0, 
      "eventualBG": 103, 
      "timestamp": "2016-12-01T14:13:20.000Z", 
      "duration": 30, 
      "tick": "+0", 
      "IOB": -0.462
    }
  }, 
  "mmtune": {
    "scanDetails": [
      [
        "916.540", 
        5, 
        -79
      ], 
      [
        "916.564", 
        5, 
        -74
      ], 
      [
        "916.588", 
        5, 
        -72
      ], 
      [
        "916.612", 
        5, 
        -72
      ], 
      [
        "916.636", 
        5, 
        -72
      ], 
      [
        "916.660", 
        5, 
        -74
      ], 
      [
        "916.684", 
        5, 
        -81
      ]
    ], 
    "setFreq": 916.636, 
    "timestamp": "2016-12-01T14:10:02.000Z", 
    "usedDefault": false
  }
}